ansiplot/__init__.py
ansiplot/canvas.py
ansiplot/rect.py
ansiplot/scaled.py
ansiplot/utils.py
ansiplot/palette/__init__.py
ansiplot/palette/colorless.py
ansiplot/palette/deuteranopia.py
ansiplot/palette/monochrome.py
ansiplot/palette/pretty.py
ansiplot/palette/protanopia.py
ansiplot/palette/tritanopia.py
tests/__init__.py
tests/test_running.py
ansiplot-0.1.3.dist-info/LICENSE.txt
ansiplot-0.1.3.dist-info/METADATA
ansiplot-0.1.3.dist-info/WHEEL
ansiplot-0.1.3.dist-info/top_level.txt
ansiplot-0.1.3.dist-info/RECORD
