Metadata-Version: 2.1
Name: ansiplot
Version: 0.1.3
Summary: Legible console plotting in Python.
Home-page: https://github.com/maniospas/ansiplot
Author: Emmanouil (Manios) Krasanakis
Author-email: maniospas@hotmail.com
Classifier: Programming Language :: Python :: 3
Classifier: License :: OSI Approved :: Apache Software License
Classifier: Operating System :: OS Independent
License-File: LICENSE.txt
